paper_speedinfo/__init__.py
paper_speedinfo/apps.py
paper_speedinfo/templates/admin/speedinfo/change_list.html
paper_speedinfo-0.0.2.dist-info/LICENSE
paper_speedinfo-0.0.2.dist-info/METADATA
paper_speedinfo-0.0.2.dist-info/WHEEL
paper_speedinfo-0.0.2.dist-info/top_level.txt
paper_speedinfo-0.0.2.dist-info/RECORD
